{
  "_fv": 10,
  "_type": "recipe",
  "definition": {
    "recipeType": "Crafting",
    "xpReward": 0.0,
    "cookingTime": 200,
    "recipeRetstackSize": 1,
    "recipeShapeless": true,
    "recipeSlots": [
      {
        "value": ""
      },
      {
        "value": "CUSTOM:Masa"
      },
      {
        "value": ""
      },
      {
        "value": ""
      },
      {
        "value": "CUSTOM:P9nao"
      },
      {
        "value": "CUSTOM:Egg"
      },
      {
        "value": ""
      },
      {
        "value": ""
      },
      {
        "value": ""
      }
    ],
    "recipeReturnStack": {
      "value": "CUSTOM:Empanadapinocruda"
    },
    "name": "r19",
    "namespace": "mod"
  }
}